easydingbot/__init__.py
easydingbot/config.py
easydingbot/main.py
easydingbot-0.0.5.dist-info/LICENSE
easydingbot-0.0.5.dist-info/METADATA
easydingbot-0.0.5.dist-info/WHEEL
easydingbot-0.0.5.dist-info/entry_points.txt
easydingbot-0.0.5.dist-info/top_level.txt
easydingbot-0.0.5.dist-info/RECORD
