Metadata-Version: 2.1
Name: easydingbot
Version: 0.0.5
Summary: A package to make dingbot easily to use
Home-page: https://github.com/seniverse/easydingbot
Author: Wentao Li
Author-email: clarmy.lee@seniverse.com
License: UNKNOWN
Platform: UNKNOWN
Classifier: Programming Language :: Python :: 3
Requires-Python: >=3.6
Requires-Dist: fire (==0.3.1)
Requires-Dist: pytest (==6.1.2)
Requires-Dist: requests (==2.25.0)
